codaicli/__init__.py
codaicli/ai_manager.py
codaicli/cli.py
codaicli/config.py
codaicli/file_manager.py
codaicli/ui.py
codaicli/utils.py
codaicli-1.0.0.dist-info/LICENSE
codaicli-1.0.0.dist-info/METADATA
codaicli-1.0.0.dist-info/WHEEL
codaicli-1.0.0.dist-info/entry_points.txt
codaicli-1.0.0.dist-info/top_level.txt
codaicli-1.0.0.dist-info/RECORD
