Metadata-Version: 2.1
Name: codaicli
Version: 1.0.0
Summary: AI-powered CLI assistant for code projects
Home-page: https://codai.app/cli
Author: Codai
Author-email: codaicli.wrist796@passmail.net
Classifier: Programming Language :: Python :: 3
Classifier: License :: OSI Approved :: MIT License
Classifier: Operating System :: OS Independent
Classifier: Development Status :: 5 - Production/Stable
Classifier: Environment :: Console
Classifier: Intended Audience :: Developers
Classifier: Topic :: Software Development :: Libraries :: Python Modules
Requires-Python: >=3.8
License-File: LICENSE
Requires-Dist: rich >=10.0.0
Requires-Dist: click >=8.0.0
Requires-Dist: python-dotenv >=0.19.0
Provides-Extra: all
Requires-Dist: openai >=1.0.0 ; extra == 'all'
Requires-Dist: google-generativeai >=0.1.0 ; extra == 'all'
Requires-Dist: anthropic >=0.5.0 ; extra == 'all'
Provides-Extra: claude
Requires-Dist: anthropic >=0.5.0 ; extra == 'claude'
Provides-Extra: gemini
Requires-Dist: google-generativeai >=0.1.0 ; extra == 'gemini'
Provides-Extra: openai
Requires-Dist: openai >=1.0.0 ; extra == 'openai'
Provides-Extra: test
Requires-Dist: pytest >=7.0.0 ; extra == 'test'
Requires-Dist: pytest-cov >=4.0.0 ; extra == 'test'
Requires-Dist: pytest-mock >=3.10.0 ; extra == 'test'
